src/__init__.py
src/visualscript/__init__.py
src/visualscript/disassembly.py
src/visualscript/temp.py
src/visualscript/test_vtoonify.py
src/visualscript/visualscript.py
src/visualscript/editor/__init__.py
src/visualscript/editor/config.py
src/visualscript/editor/editor_window.py
src/visualscript/editor/workspace_window.py
src/visualscript/editor/core/__init__.py
src/visualscript/editor/core/utils.py
src/visualscript/editor/core/models/__init__.py
src/visualscript/editor/core/models/blueprint_properties_widget.py
src/visualscript/editor/core/models/button_item.py
src/visualscript/editor/core/models/content_widget.py
src/visualscript/editor/core/models/context_menu.py
src/visualscript/editor/core/models/data_types.py
src/visualscript/editor/core/models/edge.py
src/visualscript/editor/core/models/node.py
src/visualscript/editor/core/models/properties_widget.py
src/visualscript/editor/core/models/scene.py
src/visualscript/editor/core/models/scene_clipboard.py
src/visualscript/editor/core/models/scene_history.py
src/visualscript/editor/core/models/serializable.py
src/visualscript/editor/core/models/socket.py
src/visualscript/editor/core/models/workspace.py
src/visualscript/editor/core/views/__init__.py
src/visualscript/editor/core/views/add_button.py
src/visualscript/editor/core/views/circle_button.py
src/visualscript/editor/core/views/cutline.py
src/visualscript/editor/core/views/data_types.py
src/visualscript/editor/core/views/edge.py
src/visualscript/editor/core/views/node.py
src/visualscript/editor/core/views/remove_button.py
src/visualscript/editor/core/views/scene.py
src/visualscript/editor/core/views/socket.py
src/visualscript/editor/core/views/title_text_item.py
src/visualscript/editor/core/views/workspace.py
src/visualscript/editor/nodes/__init__.py
src/visualscript/editor/nodes/attribute.py
src/visualscript/editor/nodes/call_function.py
src/visualscript/editor/nodes/call_method.py
src/visualscript/editor/nodes/cast.py
visualscript-0.0.21.dist-info/LICENSE
visualscript-0.0.21.dist-info/METADATA
visualscript-0.0.21.dist-info/WHEEL
visualscript-0.0.21.dist-info/top_level.txt
visualscript-0.0.21.dist-info/RECORD
