Metadata-Version: 2.1
Name: visualscript
Version: 0.0.21
Summary: Package for visual scripting
Author: Wachu (Adam Wachowicz)
Author-email: Wachu <adam.wachowicz@vp.pl>
License: MIT License
Project-URL: Homepage, https://github.com/Wachu94/visualscript
Project-URL: Bug Tracker, https://github.com/Wachu94/visualscript/issues
Keywords: visual,graph,blueprint
Classifier: Programming Language :: Python :: 3
Classifier: License :: OSI Approved :: MIT License
Classifier: Operating System :: OS Independent
Requires-Python: >=3.10
License-File: LICENSE
Requires-Dist: PyQt5
